ipor_fusion_sdk/MarketId.py
ipor_fusion_sdk/VaultExecuteCallFactory.py
ipor_fusion_sdk/__init__.py
ipor_fusion_sdk/fuse/AaveV3SupplyFuse.py
ipor_fusion_sdk/fuse/CompoundV3SupplyFuse.py
ipor_fusion_sdk/fuse/Erc4626SupplyFuse.py
ipor_fusion_sdk/fuse/FluidInstadappSupplyFuse.py
ipor_fusion_sdk/fuse/FuseAction.py
ipor_fusion_sdk/fuse/GearboxSupplyFuse.py
ipor_fusion_sdk/fuse/UniswapV3CollectFuse.py
ipor_fusion_sdk/fuse/UniswapV3ModifyPositionFuse.py
ipor_fusion_sdk/fuse/UniswapV3NewPositionFuse.py
ipor_fusion_sdk/fuse/UniswapV3SwapFuse.py
ipor_fusion_sdk/fuse/UniversalTokenSwapperFuse.py
ipor_fusion_sdk/fuse/__init__.py
ipor_fusion_sdk-0.1.0.dist-info/LICENSE
ipor_fusion_sdk-0.1.0.dist-info/METADATA
ipor_fusion_sdk-0.1.0.dist-info/WHEEL
ipor_fusion_sdk-0.1.0.dist-info/RECORD
