Metadata-Version: 2.1
Name: ipor-fusion-sdk
Version: 0.1.0
Summary: 
Author: Adam Mydlarz
Author-email: amydlarz@gmail.com
Requires-Python: >=3.10,<4.0
Classifier: Programming Language :: Python :: 3
Classifier: Programming Language :: Python :: 3.10
Classifier: Programming Language :: Python :: 3.11
Requires-Dist: eth-abi (==5.1.0)
Requires-Dist: eth-typing (==5.0.0)
Requires-Dist: python-dotenv (==1.0.1)
Requires-Dist: web3 (==7.3.0)
